blurring/__init__.py
blurring/__main__.py
blurring/blur.py
blurring/cli.py
blurring/hook.py
blurring/utils/__init__.py
blurring/utils/data.py
blurring/utils/misc.py
blurring/utils/temp.py
blurring-0.2.0.dist-info/LICENSE
blurring-0.2.0.dist-info/METADATA
blurring-0.2.0.dist-info/WHEEL
blurring-0.2.0.dist-info/entry_points.txt
blurring-0.2.0.dist-info/top_level.txt
blurring-0.2.0.dist-info/RECORD
