Metadata-Version: 2.1
Name: blurring
Version: 0.2.0
Summary: Censor videos automatically
Home-page: https://github.com/axju/blurring
Author: Axel Juraske
Author-email: axel.juraske@short-report.de
License: MIT
Keywords: video
Platform: UNKNOWN
Classifier: License :: OSI Approved :: MIT License
Classifier: Programming Language :: Python :: 3
Classifier: Programming Language :: Python :: 3.5
Classifier: Programming Language :: Python :: 3.6
Classifier: Programming Language :: Python :: 3.7
Classifier: Programming Language :: Python :: 3 :: Only
Classifier: Environment :: Console
Requires-Dist: ffmpeg-python
Requires-Dist: opencv-python
Requires-Dist: numpy
